bursty_dynamics/__init__.py
bursty_dynamics/scores.py
bursty_dynamics/shared_function.py
bursty_dynamics/trains.py
bursty_dynamics/visual.py
bursty_dynamics-0.1.7.dist-info/licenses/LICENSE.txt
bursty_dynamics-0.1.7.dist-info/METADATA
bursty_dynamics-0.1.7.dist-info/WHEEL
bursty_dynamics-0.1.7.dist-info/top_level.txt
bursty_dynamics-0.1.7.dist-info/RECORD
