Metadata-Version: 2.4
Name: bursty_dynamics
Version: 0.1.7
Summary: bursty_dynamics is a Python package designed to facilitate the analysis of temporal patterns in longitudinal data. It provides functions to calculate the burstiness parameter (BP) and memory coefficient (MC), detect event trains, and visualise results. 
Home-page: https://github.com/ai-multiply/bursty_dynamics
Author: Alisha Angdmebe
Author-email: alisha.angdembe1@gmail.com
License: MIT
Classifier: Programming Language :: Python :: 3
Requires-Python: >=3.6
License-File: LICENSE.txt
Requires-Dist: numpy
Requires-Dist: pandas
Requires-Dist: seaborn
Requires-Dist: matplotlib
Requires-Dist: scipy
Dynamic: author
Dynamic: author-email
Dynamic: classifier
Dynamic: description
Dynamic: description-content-type
Dynamic: home-page
Dynamic: license
Dynamic: license-file
Dynamic: requires-dist
Dynamic: requires-python
Dynamic: summary
